xpubkaleidoscope/__init__.py
xpubkaleidoscope/xpub_converter.py
xpubkaleidoscope/utils/__init__.py
xpubkaleidoscope-0.0.1.dist-info/licenses/LICENSE
xpubkaleidoscope-0.0.1.dist-info/METADATA
xpubkaleidoscope-0.0.1.dist-info/WHEEL
xpubkaleidoscope-0.0.1.dist-info/entry_points.txt
xpubkaleidoscope-0.0.1.dist-info/top_level.txt
xpubkaleidoscope-0.0.1.dist-info/RECORD
