Metadata-Version: 2.4
Name: xpubkaleidoscope
Version: 0.0.1
Summary: A Python utility for converting Bitcoin Extended Public Keys between different formats
Home-page: https://github.com/valerio-vaccaro/XPubKaleidoscope
Author: Valerio Vaccaro
Author-email: Valerio Vaccaro <valerio.vaccaro@gmail.com>
Project-URL: Homepage, https://github.com/valerio-vaccaro/XPubKaleidoscope
Project-URL: Bug Tracker, https://github.com/valerio-vaccaro/XPubKaleidoscope/issues
Classifier: Programming Language :: Python :: 3
Classifier: License :: OSI Approved :: MIT License
Classifier: Operating System :: OS Independent
Classifier: Development Status :: 4 - Beta
Classifier: Intended Audience :: Developers
Classifier: Topic :: Software Development :: Libraries :: Python Modules
Classifier: Topic :: Security :: Cryptography
Requires-Python: >=3.6
License-File: LICENSE
Requires-Dist: base58
Dynamic: license-file
